{
    "get": {
        "tags": [
            "User - login"
        ],
        "summary": "Login",
        "description": "Retorna uma lista de Usuario",
        "responses": {
            "200": {
                "description": "OK",
                "content": {
                    "application/json": {
                        "schema": {
                            "type": "array",
                            "items": {
                                "properties": {
                                    "login_id": {
                                        "type": "number"
                                    }
                                }
                            }
                        }
                    }
                }
            },
            "400": {
                "$ref": "../../errors/400.json"
            }
        }
    }
}